Workbook
Name AllottedFunds: '[2]Project Details'!#REF!
Name ColumnTitle1: #REF!
Name ColumnTitle2: #REF!
Name ColumnTitleRegion1..E6.1: #REF!
Name Display_Week: #REF!
Name FirstDayofTheMonth: #REF!
Name FundsRemaining: INDEX(#REF!,ROWS(#REF!),1)
Name FundsRemainingLabel: '[2]Project Details'!#REF!
Name FundsUsed: '[2]Project Details'!#REF!
Name FundsUsedLabel: '[2]Project Details'!#REF!
Name Project_last_entry: #REF!
Name Project_Start: #REF!
Name Project_start_row: #REF!
Name RowTitleRegion1..C11: '[2]Project Details'!$B$4
Name SortCodes: #REF!
Name SortCodes: #REF!
Name Staff2: #REF!
Name TeamName: #REF!
Name Title1: '[2]Project Details'!#REF!
Name ValidBanks: #REF!
Name ValidBanks: #REF!
Name Workweek: #REF!
Name WorkweekHours: #REF!

Sheet a
E7: =CONCATENATE('[2]Project Details'!C19, " ",'[2]Project Details'!B19) -> Jigawa State
C9: ='[2]Project Details'!C20 -> PRIMARY HEALTHCARE DEVELOPMENT AGENCY Block B New State Secretariat Complex XYZ - JABC State.
D11: Email: | E11: ='[2]Project Details'!C21 -> phc@abcstate.gov.ng
B13: PHCDA/PHC/IMM/VOL1/150 | H13: =TODAY() -> 46262
B15: Chief of Field Office,
B16: UNICEF Kano office,
B17: Kano.
B19: SUBMISSION OF RETIREMENT DOCUMENT, ANNEX 4 AND FACE FORM FOR THE
B23: I write to notify you of the submission of retirement documents for the following
B24: activities. Attached are relevant documents for your necessary action
B26: SN | C26: ACTIVITY | H26: AMOUNT
B27: .A. | C27: =IF(B27=0,"",VLOOKUP(B27,b!$A$16:$K$25,2,FALSE)) -> Leadership, Management and Coordination | H27: =IF(B27=0,"",VLOOKUP(B27,b!$A$16:$K$25,10,FALSE)) -> 2440000
B28: .B. | C28: =IF(B28=0,"",VLOOKUP(B28,b!$A$16:$K$25,2,FALSE)) -> Demand Generation | H28: =IF(B28=0,"",VLOOKUP(B28,b!$A$16:$K$25,10,FALSE)) -> 23200000
B29: .C. | C29: =IF(B29=0,"",VLOOKUP(B29,b!$A$16:$K$25,2,FALSE)) -> Human Resource for Health | H29: =IF(B29=0,"",VLOOKUP(B29,b!$A$16:$K$25,10,FALSE)) -> 2640000
B30: .D. | C30: =IF(B30=0,"",VLOOKUP(B30,b!$A$16:$K$25,2,FALSE)) -> Service Delivery | H30: =IF(B30=0,"",VLOOKUP(B30,b!$A$16:$K$25,10,FALSE)) -> 3280000
B31: .E. | C31: =IF(B31=0,"",VLOOKUP(B31,b!$A$16:$K$25,2,FALSE)) -> Supply Chain | H31: =IF(B31=0,"",VLOOKUP(B31,b!$A$16:$K$25,10,FALSE)) -> 2640000
B32: .F. | C32: =IF(B32=0,"",VLOOKUP(B32,b!$A$16:$K$25,2,FALSE)) -> Health Financing | H32: =IF(B32=0,"",VLOOKUP(B32,b!$A$16:$K$25,10,FALSE)) -> 3120000
B33: .G. | C33: =IF(B33=0,"",VLOOKUP(B33,b!$A$16:$K$25,2,FALSE)) -> Health Information Management System | H33: =IF(B33=0,"",VLOOKUP(B33,b!$A$16:$K$25,10,FALSE)) -> 2640000
B34: 0 | C34: =IF(B34=0,"",VLOOKUP(B34,b!$A$16:$K$25,2,FALSE)) | H34: =IF(B34=0,"",VLOOKUP(B34,b!$A$16:$K$25,10,FALSE))
B35: 0 | C35: =IF(B35=0,"",VLOOKUP(B35,b!$A$16:$K$25,2,FALSE)) | H35: =IF(B35=0,"",VLOOKUP(B35,b!$A$16:$K$25,10,FALSE))
B36: 0 | H36: =IF(B36=0,"",VLOOKUP(B36,b!$A$16:$K$25,10,FALSE))
C37: GRANT TOTAL | H37: =SUM(H27:H36) -> 39960000
B39: Best Regards
B42: ='[2]Project Details'!C22 -> Dr. shehu sambo
B43: ='[2]Project Details'!C23 -> Executive Secretory

Sheet b
B1: Funding Authorization and Certificate of Expenditure | K1: UN Agency: | L1: UNICEF | P1: Date: | Q1: =TODAY() -> 46262
B3: Country: | E3: NIGERIA | P3: Type of Request:
B4: Programme Code & Title: 03 Programme Effectiveness | F4: Outcome 1:Maternal Newborn and Child Health | P4: X□ Direct Cash Transfer (DCT)
B5: Project Code & Title: | F5: Outcome 1.1 : HSS | P5: □ Reimbursement
B6: Responsible Officer(s): | F6: Dr Shamsuddeen Yahaya | P6: □ Direct payment
B7: Implementing Partner: | F7: Katsina State Primary Health Care Agency
E9: Currency: ___Naira (N)____ | J9: REPORTING | O9: REQUESTS / AUTHORIZATIONS
B11: Activity Description from AWP with Duration | H11: Coding for UNDP, UNFPA and WFP | J11: Authorised Amount | K11: Actual Project Expenditure | L11: Expenditures accepted by Agency | M11: Balance | O11: New Request Period & Amount | P11: Authorised Amount | Q11: Outstanding Authorised Amount
J12: 45163
J13: A | K13: B | L13: C | M13: D = A - C | O13: E | P13: F | Q13: G = D + F
B15: =[1]c!E2 -> ANNEX 4 : ITEMIZED COST ESTIMATE/B U D G E T FOR GAVI HSS ACTIVITIES (APRIL TO JUNE 2024)
A16: .A. | B16: =IF(A16=0,"",VLOOKUP(A16,[1]c!$B$8:$E$188,4,FALSE)) -> Leadership, Management and Coordination | J16: =IF(A16=0,"",VLOOKUP(A16,[1]c!$B$8:$E$188,3,FALSE)) -> 2440000 | K16: =IF(A16=0,"",VLOOKUP(A16,[1]c!$B$8:$E$188,2,FALSE)) -> 2280000
A17: .B. | B17: =IF(A17=0,"",VLOOKUP(A17,[1]c!$B$8:$E$188,4,FALSE)) -> Demand Generation | J17: =IF(A17=0,"",VLOOKUP(A17,[1]c!$B$8:$E$188,3,FALSE)) -> 23200000 | K17: =IF(A17=0,"",VLOOKUP(A17,[1]c!$B$8:$E$188,2,FALSE)) -> 21280000
A18: .C. | B18: =IF(A18=0,"",VLOOKUP(A18,[1]c!$B$8:$E$188,4,FALSE)) -> Human Resource for Health | J18: =IF(A18=0,"",VLOOKUP(A18,[1]c!$B$8:$E$188,3,FALSE)) -> 2640000 | K18: =IF(A18=0,"",VLOOKUP(A18,[1]c!$B$8:$E$188,2,FALSE)) -> 2640000
A19: .D. | B19: =IF(A19=0,"",VLOOKUP(A19,[1]c!$B$8:$E$188,4,FALSE)) -> Service Delivery | J19: =IF(A19=0,"",VLOOKUP(A19,[1]c!$B$8:$E$188,3,FALSE)) -> 3280000 | K19: =IF(A19=0,"",VLOOKUP(A19,[1]c!$B$8:$E$188,2,FALSE)) -> 3280000
A20: .E. | B20: =IF(A20=0,"",VLOOKUP(A20,[1]c!$B$8:$E$188,4,FALSE)) -> Supply Chain | J20: =IF(A20=0,"",VLOOKUP(A20,[1]c!$B$8:$E$188,3,FALSE)) -> 2640000 | K20: =IF(A20=0,"",VLOOKUP(A20,[1]c!$B$8:$E$188,2,FALSE)) -> 2640000
A21: .F. | B21: =IF(A21=0,"",VLOOKUP(A21,[1]c!$B$8:$E$188,4,FALSE)) -> Health Financing | J21: =IF(A21=0,"",VLOOKUP(A21,[1]c!$B$8:$E$188,3,FALSE)) -> 3120000 | K21: =IF(A21=0,"",VLOOKUP(A21,[1]c!$B$8:$E$188,2,FALSE)) -> 3120000
A22: .G. | B22: =IF(A22=0,"",VLOOKUP(A22,[1]c!$B$8:$E$188,4,FALSE)) -> Health Information Management System | J22: =IF(A22=0,"",VLOOKUP(A22,[1]c!$B$8:$E$188,3,FALSE)) -> 2640000 | K22: =IF(A22=0,"",VLOOKUP(A22,[1]c!$B$8:$E$188,2,FALSE)) -> 2640000
A23: .C. | B23: =IF(A23=0,"",VLOOKUP(A23,[1]c!$B$8:$E$188,4,FALSE)) -> Human Resource for Health | J23: =IF(A23=0,"",VLOOKUP(A23,[1]c!$B$8:$E$188,3,FALSE)) -> 2640000 | K23: =IF(A23=0,"",VLOOKUP(A23,[1]c!$B$8:$E$188,2,FALSE)) -> 2640000
A24: 0 | B24: =IF(A24=0,"",VLOOKUP(A24,[1]c!$B$8:$E$188,4,FALSE)) | J24: =IF(A24=0,"",VLOOKUP(A24,[1]c!$B$8:$E$188,3,FALSE)) | K24: =IF(A24=0,"",VLOOKUP(A24,[1]c!$B$8:$E$188,2,FALSE))
B26: Total | J26: =SUM(J15:J25) -> 42600000 | K26: =SUM(K15:K25) -> 40520000 | O26: =SUM(O15:O25) -> 0
B28: CERTIFICATION
B29: The undersigned authorized officer of the above-mentioned implementing institution hereby certifies that:
B30: □ | C30: The funding request shown above represents estimated expenditures as per AWP and itemized cost estimates attached.
B31: □X | C31: The actual expenditures for the period stated herein has been disbursed in accordance with the AWP and request with itemized cost estimates. The detailed accounting documents for these expenditures can be made available for examination, when required, for the period of five years from the date of the provision of funds.
B32: Date Submitted: | J32: Name/Sign: | M32: Title/Official Stamp:
B34: NOTES: | D34: *Shaded areas to be completed by the UN Agency and non-shaded areas to be completed by the counterpart.
B37: FOR AGENCY USE ONLY:
B38: FOR ALL AGENCIES | I38: FOR UNICEF USE ONLY | O38: FOR UNFPA USE ONLY
B39: CERTIFICATION | I39: Account Charges | L39: Liquidation Information | O39: New Funding Release
B40: Name/Sign: | D40: ________________________________________________ | I40: Cash Transfer Reference: | L40: DCT Reference:
B41: Title: | D41: ________________________________________________ | I41: CRQ ref. no., Voucher ref. no. | L41: CRQ ref. no., Liquidation ref. no. | O41: Activity 1 | P41: 0
B42: Date: | D42: ________________________________________________
B43: APPROVAL | I43: GL codes: | L43: DCT Amount | M43: 0 | O43: Activity 2 | P43: 0
B44: Name/Sign: | D44: ________________________________________________ | I44: Training | K44: 0 | L44: Less:
I45: Travel | K45: 0 | L45: Liquidation
B46: Title: | D46: ________________________________________________ | I46: Meetings & Conferences | K46: 0 | L46: Amount | M46: 0
I47: Other Cash Transfers | K47: 0
B48: Date: | D48: ________________________________________________ | I48: Total | K48: =SUM(K44:K47) -> 0 | L48: Balance | M48: =+M43+M46 -> 0 | O48: Total | P48: =+P42+P46 -> 0

Sheet c
B2: ANNEX 4 : ITEMIZED COST ESTIMATE/B U D G E T FOR GAVI HSS ACTIVITIES (APRIL TO JUNE 2024)
B3: NAME OF IMPLEMENTING PARTNER: Katsina State Primary Health Agency.
B4: NAME OF PROJECT: Katsina State Proposal for Quarter 1 Activities | G4: Responsible Prog. Officer:
G5: Shaima'u Kabir
B6: KATSINA STATE PHC HSS MOU
B7: Operational Logistic inputs (Waste Management ) | C7: BUDGET | H7: ACTUAL | M7: VARIANCE
A8: .A. | B8: Leadership, Management and Coordination | C8: Quantity | D8: No of Days | E8: Frequency | F8: Rate | G8: Total | H8: Quantity | I8: No of Days | J8: Frequency | K8: Rate | L8: Total | M8: Quantity | N8: No of Days | O8: Frequency | P8: Rate | Q8: Total
A9: 1 | B9: Quarterly STF Review Meeting
A10: i | B10: Hall hire | C10: 2 | D10: 20 | E10: 1 | F10: 4000 | G10: =PRODUCT(C10:F10) -> 160000 | H10: 2 | I10: 20 | J10: 1 | K10: 4000 | L10: =PRODUCT(H10:K10) -> 160000 | M10: 2 | N10: 20 | O10: 1 | P10: 4000 | Q10: =PRODUCT(M10:P10) -> 160000
A11: ii | B11: 2 tea breaks | C11: 2 | D11: 20 | E11: 1 | F11: 4000 | G11: =PRODUCT(C11:F11) -> 160000 | H11: 2 | I11: 20 | J11: 1 | K11: 4000 | L11: =PRODUCT(H11:K11) -> 160000 | M11: 2 | N11: 20 | O11: 1 | P11: 4000 | Q11: =PRODUCT(M11:P11) -> 160000
A12: iii | B12: Lunch | C12: 2 | D12: 20 | E12: 1 | F12: 4000 | G12: =PRODUCT(C12:F12) -> 160000 | H12: 2 | I12: 20 | J12: 1 | K12: 4000 | L12: =PRODUCT(H12:K12) -> 160000 | M12: 2 | N12: 20 | O12: 1 | P12: 4000 | Q12: =PRODUCT(M12:P12) -> 160000
A13: iv | B13: Stationeries | C13: 2 | D13: 20 | E13: 1 | F13: 4000 | G13: =PRODUCT(C13:F13) -> 160000 | H13: 2 | I13: 20 | J13: 1 | K13: 4000 | L13: =PRODUCT(H13:K13) -> 160000 | M13: 2 | N13: 20 | O13: 1 | P13: 4000 | Q13: =PRODUCT(M13:P13) -> 160000
A14: v | B14: Transport | C14: 2 | D14: 20 | E14: 1 | F14: 4000 | G14: =PRODUCT(C14:F14) -> 160000 | H14: 2 | I14: 20 | J14: 1 | K14: 4000 | L14: =PRODUCT(H14:K14) -> 160000 | M14: 2 | N14: 20 | O14: 1 | P14: 4000 | Q14: =PRODUCT(M14:P14) -> 160000
A17: H | C17: Quantity | D17: No of Days | E17: Frequency | F17: Rate | G17: Total | H17: Quantity | I17: No of Days | J17: Frequency | K17: Rate | L17: Total | M17: Quantity | N17: No of Days | O17: Frequency | P17: Rate | Q17: Total
B18: =CONCATENATE("Sub Total ",B17) -> Sub Total
A19: I
B20: =CONCATENATE("Sub Total ",B19) -> Sub Total
A21: J | C21: Quantity | D21: No of Days | E21: Frequency | F21: Rate | G21: Total Amount Payable(N) | H21: Quantity | I21: No of Days | J21: Frequency | K21: Rate | L21: Total Amount Payable(N) | M21: Quantity | N21: No of Days | O21: Frequency | P21: Rate | Q21: Total Amount Payable(N)
B22: =CONCATENATE("Sub Total ",B21) -> Sub Total
B23: =CONCATENATE("Sub Total ",B17) -> Sub Total
B24: =CONCATENATE("Grand Total ",A6) -> Grand Total | G24: =G16+#REF!+#REF!+#REF!+#REF!+#REF!+#REF! -> #REF! | L24: =L16+#REF!+#REF!+#REF!+#REF!+#REF!+#REF! -> #REF! | Q24: =Q16+#REF!+#REF!+#REF!+#REF!+#REF!+#REF! -> #REF!
B26: Implementing Partner's Designated Official:
F27: Title/Name And Signature
F28: Official Seal Or Stamp
F29: Date
B30: For UNICEF Use Only:
B31: Certifying Officer: | F31: Approving Officer:
B32: Title: | F32: Title:
B33: Name and Signature | F33: Name and Signature
B34: Date: | F34: Date:
